pyacgt/__init__.py
pyacgt/acme.py
pyacgt/examples.py
pyacgt/util.py
pyacgt-0.1.2.data/data/bin/acme_linux
pyacgt-0.1.2.data/data/bin/acme_osx
pyacgt-0.1.2.data/data/bin/acme_win.exe
pyacgt-0.1.2.dist-info/LICENSE
pyacgt-0.1.2.dist-info/METADATA
pyacgt-0.1.2.dist-info/WHEEL
pyacgt-0.1.2.dist-info/top_level.txt
pyacgt-0.1.2.dist-info/RECORD
