Metadata-Version: 2.1
Name: pyacgt
Version: 0.1.2
Summary: Python interface to ACME
Home-page: https://github.com/nick5435/pyacgt
Author: Nick Meyer
Author-email: nmeyer5435@gmail.com
License: GPLv3+
Keywords: mathematics,group-theory,andrews-curtis
Classifier: Development Status :: 3 - Alpha
Classifier: Programming Language :: Python :: 3.7
Classifier: Programming Language :: Python :: 3.8
Classifier: Programming Language :: Python :: 3.9
Classifier: Programming Language :: Python :: 3.10
Classifier: Programming Language :: Python :: 3
Classifier: Natural Language :: English
Classifier: Environment :: Console
Classifier: Topic :: Scientific/Engineering :: Mathematics
Classifier: Operating System :: Microsoft :: Windows
Classifier: Operating System :: POSIX :: Linux
Classifier: Operating System :: Unix
Classifier: Operating System :: MacOS
Classifier: Topic :: Software Development :: Libraries :: Python Modules
Classifier: Topic :: Education
Classifier: Intended Audience :: Science/Research
Classifier: License :: OSI Approved :: GNU General Public License v3 or later (GPLv3+)
Requires-Python: >=3.7.0
License-File: LICENSE
Requires-Dist: typing (>=3.7.0)
Requires-Dist: typing-extensions (>=4.0.0)
